globalemu/__init__.py
globalemu/cmSim.py
globalemu/downloads.py
globalemu/eval.py
globalemu/gui_config.py
globalemu/losses.py
globalemu/models.py
globalemu/network.py
globalemu/plotter.py
globalemu/preprocess.py
globalemu/resample.py
globalemu-1.8.1.data/scripts/globalemu
globalemu-1.8.1.dist-info/LICENSE
globalemu-1.8.1.dist-info/METADATA
globalemu-1.8.1.dist-info/WHEEL
globalemu-1.8.1.dist-info/top_level.txt
globalemu-1.8.1.dist-info/RECORD
