Metadata-Version: 2.1
Name: globalemu
Version: 1.8.1
Summary: globalemu: Robust and Fast Global 21-cm Signal Emulation
Home-page: https://github.com/htjb/globalemu
Author: Harry T. J. Bevins
Author-email: htjb2@cam.ac.uk
License: MIT
Classifier: Intended Audience :: Science/Research
Classifier: Natural Language :: English
Classifier: License :: OSI Approved :: MIT License
Classifier: Programming Language :: Python :: 3.6
Classifier: Programming Language :: Python :: 3.7
Classifier: Programming Language :: Python :: 3.8
Classifier: Topic :: Scientific/Engineering
Classifier: Topic :: Scientific/Engineering :: Astronomy
Classifier: Topic :: Scientific/Engineering :: Physics
License-File: LICENSE
Requires-Dist: numpy
Requires-Dist: pandas
Requires-Dist: matplotlib
Requires-Dist: Pillow
Requires-Dist: tensorflow ; sys_platform != "darwin"
Requires-Dist: tensorflow-macos ; sys_platform == "darwin"
Provides-Extra: docs
Requires-Dist: sphinx ; extra == 'docs'
Requires-Dist: sphinx-rtd-theme ; extra == 'docs'
Requires-Dist: numpydoc ; extra == 'docs'
Requires-Dist: packaging ; extra == 'docs'
